sslcertchecker/__init__.py
sslcertchecker/checker.py
sslcertchecker_sebastian_stigler-2.1.0.dist-info/LICENSE.txt
sslcertchecker_sebastian_stigler-2.1.0.dist-info/METADATA
sslcertchecker_sebastian_stigler-2.1.0.dist-info/WHEEL
sslcertchecker_sebastian_stigler-2.1.0.dist-info/entry_points.txt
sslcertchecker_sebastian_stigler-2.1.0.dist-info/top_level.txt
sslcertchecker_sebastian_stigler-2.1.0.dist-info/RECORD
