Metadata-Version: 2.1
Name: sslcertchecker-sebastian-stigler
Version: 2.1.0
Summary: Observe how long a ssl certificate is valid for certain urls.
Home-page: https://in-stigler.htw-aalen.de/gitea/tools/sslcertchecker
Author: Sebastian Stigler
Author-email: sebastian.stigler@hs-aalen.de
License: MIT
Project-URL: Source, https://in-stigler.htw-aalen.de/gitea/tools/sslcertchecker
Platform: any
Classifier: Development Status :: 4 - Beta
Classifier: Programming Language :: Python
License-File: LICENSE.txt
Requires-Dist: colorama
Requires-Dist: pyyaml
Requires-Dist: importlib-metadata ; python_version < "3.8"
Provides-Extra: testing
Requires-Dist: setuptools ; extra == 'testing'
Requires-Dist: pytest ; extra == 'testing'
Requires-Dist: pytest-cov ; extra == 'testing'
